{"nodes": [{"id": "churchprefs", "label": "churchPrefs.ts", "file_type": "code", "source_file": "sunday-tally\\src\\lib\\churchPrefs.ts", "source_location": "L1"}, {"id": "churchprefs_readchurchprefs", "label": "readChurchPrefs()", "file_type": "code", "source_file": "sunday-tally\\src\\lib\\churchPrefs.ts", "source_location": "L37"}, {"id": "churchprefs_ismissingcolumn", "label": "isMissingColumn()", "file_type": "code", "source_file": "sunday-tally\\src\\lib\\churchPrefs.ts", "source_location": "L51"}, {"id": "churchprefs_savechurchprefs", "label": "saveChurchPrefs()", "file_type": "code", "source_file": "sunday-tally\\src\\lib\\churchPrefs.ts", "source_location": "L63"}], "edges": [{"source": "churchprefs", "target": "supabase_js", "relation": "imports_from", "confidence": "EXTRACTED", "source_file": "sunday-tally\\src\\lib\\churchPrefs.ts", "source_location": "L22", "weight": 1.0}, {"source": "churchprefs", "target": "churchprefs_readchurchprefs", "relation": "contains", "confidence": "EXTRACTED", "source_file": "sunday-tally\\src\\lib\\churchPrefs.ts", "source_location": "L37", "weight": 1.0}, {"source": "churchprefs", "target": "churchprefs_ismissingcolumn", "relation": "contains", "confidence": "EXTRACTED", "source_file": "sunday-tally\\src\\lib\\churchPrefs.ts", "source_location": "L51", "weight": 1.0}, {"source": "churchprefs", "target": "churchprefs_savechurchprefs", "relation": "contains", "confidence": "EXTRACTED", "source_file": "sunday-tally\\src\\lib\\churchPrefs.ts", "source_location": "L63", "weight": 1.0}, {"source": "churchprefs_savechurchprefs", "target": "churchprefs_ismissingcolumn", "relation": "calls", "confidence": "EXTRACTED", "source_file": "sunday-tally\\src\\lib\\churchPrefs.ts", "source_location": "L79", "weight": 1.0}]}