{"nodes": [{"id": "questioncard", "label": "QuestionCard.tsx", "file_type": "code", "source_file": "sunday-tally\\src\\app\\onboarding\\import\\review\\components\\QuestionCard.tsx", "source_location": "L1"}, {"id": "questioncard_handlefreetext", "label": "handleFreeText()", "file_type": "code", "source_file": "sunday-tally\\src\\app\\onboarding\\import\\review\\components\\QuestionCard.tsx", "source_location": "L38"}], "edges": [{"source": "questioncard", "target": "react", "relation": "imports_from", "confidence": "EXTRACTED", "source_file": "sunday-tally\\src\\app\\onboarding\\import\\review\\components\\QuestionCard.tsx", "source_location": "L3", "weight": 1.0}, {"source": "questioncard", "target": "stagea_validate", "relation": "imports_from", "confidence": "EXTRACTED", "source_file": "sunday-tally\\src\\app\\onboarding\\import\\review\\components\\QuestionCard.tsx", "source_location": "L4", "weight": 1.0}, {"source": "questioncard", "target": "questioncard_handlefreetext", "relation": "contains", "confidence": "EXTRACTED", "source_file": "sunday-tally\\src\\app\\onboarding\\import\\review\\components\\QuestionCard.tsx", "source_location": "L38", "weight": 1.0}]}